{
  "reflection": [
    {
      "type": "ankol.mod.merger.AppMain",
      "jniAccessible": true,
      "allDeclaredConstructors": true,
      "allDeclaredMethods": true,
      "allDeclaredFields": true
    },
    {
      "type": "ankol.mod.merger.merger.scr.TechlandScrFileMerger",
      "allDeclaredConstructors": true,
      "allDeclaredMethods": true,
      "allDeclaredFields": true
    },
    {
      "type": "ankol.mod.merger.merger.xml.TechlandXmlFileMerger",
      "allDeclaredConstructors": true,
      "allDeclaredMethods": true,
      "allDeclaredFields": true
    },
    {
      "type": "ch.qos.logback.core.ConsoleAppender",
      "allDeclaredConstructors": true,
      "allDeclaredFields": true,
      "allDeclaredMethods": true
    },
    {
      "type": "ch.qos.logback.classic.AsyncAppender",
      "allDeclaredConstructors": true,
      "allDeclaredFields": true,
      "allDeclaredMethods": true
    },
    {
      "type": "ch.qos.logback.classic.filter.ThresholdFilter",
      "allDeclaredConstructors": true,
      "allDeclaredFields": true,
      "allDeclaredMethods": true
    },
    {
      "type": "ch.qos.logback.core.encoder.LayoutWrappingEncoder",
      "allDeclaredConstructors": true,
      "allDeclaredFields": true,
      "allDeclaredMethods": true
    },
    {
      "type": "ch.qos.logback.core.UnsynchronizedAppenderBase",
      "allDeclaredConstructors": true,
      "allDeclaredFields": true,
      "allDeclaredMethods": true
    },
    {
      "type": "ch.qos.logback.core.AsyncAppenderBase",
      "allDeclaredConstructors": true,
      "allDeclaredFields": true,
      "allDeclaredMethods": true
    }
  ],
  "resources": [
    {
      "glob": "i18n/**.properties"
    },
    {
      "glob": "logback.xml"
    }
  ]
}